dhg_bench-0.1.2.dist-info/licenses/LICENSE
dhgbench/__init__.py
dhgbench/main.py
dhgbench/parameter_parser.py
dhgbench/lib_dataset/__init__.py
dhgbench/lib_dataset/convert_datasets_to_pygDataset.py
dhgbench/lib_dataset/data_base.py
dhgbench/lib_dataset/data_perturbation.py
dhgbench/lib_dataset/edge_loaders.py
dhgbench/lib_dataset/edge_sampler.py
dhgbench/lib_dataset/hg_loaders.py
dhgbench/lib_dataset/load_other_datasets.py
dhgbench/lib_dataset/preprocessing.py
dhgbench/lib_models/__init__.py
dhgbench/lib_models/HNN/__init__.py
dhgbench/lib_models/HNN/allset.py
dhgbench/lib_models/HNN/cegnn.py
dhgbench/lib_models/HNN/dphgnn.py
dhgbench/lib_models/HNN/edgnn.py
dhgbench/lib_models/HNN/ehnn.py
dhgbench/lib_models/HNN/ehnn_linear.py
dhgbench/lib_models/HNN/ehnn_transformer.py
dhgbench/lib_models/HNN/hgnn.py
dhgbench/lib_models/HNN/hjrl.py
dhgbench/lib_models/HNN/hnhn.py
dhgbench/lib_models/HNN/hypergcn.py
dhgbench/lib_models/HNN/hypergt.py
dhgbench/lib_models/HNN/hypernd.py
dhgbench/lib_models/HNN/legcn.py
dhgbench/lib_models/HNN/mlp.py
dhgbench/lib_models/HNN/phenomnn.py
dhgbench/lib_models/HNN/phenomnns.py
dhgbench/lib_models/HNN/preprocessing.py
dhgbench/lib_models/HNN/sheafhypergnn.py
dhgbench/lib_models/HNN/tfhnn.py
dhgbench/lib_models/HNN/tmphn.py
dhgbench/lib_models/HNN/unigcn2.py
dhgbench/lib_models/HNN/unigencoder.py
dhgbench/lib_models/HNN/unignn.py
dhgbench/lib_models/HNN/utils.py
dhgbench/lib_utils/__init__.py
dhgbench/lib_utils/aggregator.py
dhgbench/lib_utils/eval_agent.py
dhgbench/lib_utils/exp_agent.py
dhgbench/lib_utils/metrics.py
dhgbench/lib_utils/train_agent.py
dhgbench/lib_utils/utils.py
dhgbench/lib_yamls/edge_yamls/config_alldeepsets.yaml
dhgbench/lib_yamls/edge_yamls/config_allsetformer.yaml
dhgbench/lib_yamls/edge_yamls/config_dphgnn.yaml
dhgbench/lib_yamls/edge_yamls/config_edhnn.yaml
dhgbench/lib_yamls/edge_yamls/config_ehnn.yaml
dhgbench/lib_yamls/edge_yamls/config_hcha.yaml
dhgbench/lib_yamls/edge_yamls/config_hgnn.yaml
dhgbench/lib_yamls/edge_yamls/config_hjrl.yaml
dhg_bench-0.1.2.dist-info/METADATA
dhg_bench-0.1.2.dist-info/WHEEL
dhg_bench-0.1.2.dist-info/entry_points.txt
dhg_bench-0.1.2.dist-info/top_level.txt
dhg_bench-0.1.2.dist-info/RECORD
