Metadata-Version: 2.4
Name: dhg-bench
Version: 0.1.2
Summary: An open and unified pipeline for Deep Hypergraph Learning (DHGL)
Maintainer: DHG-Bench Team
License: MIT License
Project-URL: Homepage, https://github.com/Coco-Hut/DHG-Bench
Project-URL: Bug Tracker, https://github.com/Coco-Hut/DHG-Bench/issues
Requires-Python: >=3.9
License-File: LICENSE
Requires-Dist: numpy<2.0,>=1.20
Requires-Dist: scikit-learn>=1.0
Requires-Dist: pyyaml
Provides-Extra: dev
Requires-Dist: ipdb; extra == "dev"
Requires-Dist: deeprobust==0.2.11; extra == "dev"
Dynamic: license-file
